graph_scheduler/__init__.py
graph_scheduler/_version.py
graph_scheduler/condition.py
graph_scheduler/scheduler.py
graph_scheduler/time.py
graph_scheduler/utilities.py
graph_scheduler-1.2.2.dist-info/LICENSE.txt
graph_scheduler-1.2.2.dist-info/METADATA
graph_scheduler-1.2.2.dist-info/WHEEL
graph_scheduler-1.2.2.dist-info/top_level.txt
graph_scheduler-1.2.2.dist-info/RECORD
