Metadata-Version: 2.1
Name: graph-scheduler
Version: 1.2.2
Summary: A graph-based scheduler of nodes based on structure and conditions
Home-page: https://github.com/kmantel/graph-scheduler
Author: Katherine Mantel, Princeton University
Author-email: kmantel@princeton.edu
License: UNKNOWN
Project-URL: Bug Tracker, https://github.com/kmantel/graph-scheduler/issues
Platform: UNKNOWN
Classifier: Development Status :: 5 - Production/Stable
Classifier: License :: OSI Approved :: Apache Software License
Classifier: Operating System :: OS Independent
Classifier: Programming Language :: Python :: 3.7
Classifier: Programming Language :: Python :: 3.8
Classifier: Programming Language :: Python :: 3.9
Classifier: Programming Language :: Python :: 3.10
Classifier: Programming Language :: Python :: 3.11
Requires-Python: >=3.7
License-File: LICENSE.txt
Requires-Dist: networkx
Requires-Dist: numpy (>=1.19.0)
Requires-Dist: pandas
Requires-Dist: pint
Requires-Dist: scipy
Requires-Dist: toposort
Provides-Extra: dev
Requires-Dist: pydot ; extra == 'dev'
Requires-Dist: pytest ; extra == 'dev'
Requires-Dist: pytest-cov ; extra == 'dev'
Requires-Dist: pytest-helpers-namespace ; extra == 'dev'
Requires-Dist: pytest-pycodestyle ; extra == 'dev'
Requires-Dist: pytest-pydocstyle ; extra == 'dev'
Requires-Dist: pytest-xdist ; extra == 'dev'
Provides-Extra: docs
Requires-Dist: m2r2 ; extra == 'docs'
Requires-Dist: sphinx (<7) ; extra == 'docs'
Requires-Dist: sphinx-autodoc-typehints ; extra == 'docs'
Requires-Dist: sphinx-rtd-theme ; extra == 'docs'
